topacademy_api/.DS_Store
topacademy_api/__init__.py
topacademy_api/async_.py
topacademy_api/sync.py
topacademy_api-1.2.dist-info/licenses/LICENSE
topacademy_api-1.2.dist-info/METADATA
topacademy_api-1.2.dist-info/WHEEL
topacademy_api-1.2.dist-info/RECORD
