Metadata-Version: 2.4
Name: topacademy_api
Version: 1.2
Summary: A library for Python that provides an easy interface to interact with the TOP Academy resources
License: GPL-2.0
License-File: LICENSE
Author: Egor A. Balenko
Author-email: contact@dust0n.ru
Requires-Python: >=3.12,<4.0
Classifier: License :: OSI Approved :: GNU General Public License v2 (GPLv2)
Classifier: Programming Language :: Python :: 3
Classifier: Programming Language :: Python :: 3.12
Classifier: Programming Language :: Python :: 3.13
Classifier: Programming Language :: Python :: 3.14
Requires-Dist: requests (>=2.32.0,<3.0.0)
